tempoo/__init__.py
tempoo/doy.py
tempoo/gps.py
tempoo/local.py
tempoo/timeline.py
tempoo/timetick.py
tempoo/utc.py
tempoo/version.py
tempoo/windows.py
tempoo/bin/doy
tempoo-1.2.3.dist-info/licenses/LICENSE
tempoo-1.2.3.dist-info/METADATA
tempoo-1.2.3.dist-info/WHEEL
tempoo-1.2.3.dist-info/entry_points.txt
tempoo-1.2.3.dist-info/top_level.txt
tempoo-1.2.3.dist-info/RECORD
