Metadata-Version: 2.4
Name: tempoo
Version: 1.2.3
Author-email: Maximilien Lehujeur <maximilien.lehujeur@univ-eiffel.fr>
License: MIT
Classifier: Programming Language :: Python :: 3
Classifier: Operating System :: POSIX :: Linux
Classifier: Operating System :: Microsoft :: Windows
Requires-Python: <3.13,>=3.7
License-File: LICENSE
Requires-Dist: numpy
Requires-Dist: matplotlib
Requires-Dist: pytest
Requires-Dist: pytz
Dynamic: license-file
